enpt_enmapboxapp/__init__.py
enpt_enmapboxapp/_enpt_alg_base.py
enpt_enmapboxapp/enpt_algorithm.py
enpt_enmapboxapp/enpt_enmapboxapp.py
enpt_enmapboxapp/enpt_external_algorithm.py
enpt_enmapboxapp/version.py
enpt_enmapboxapp-0.7.6.data/scripts/enpt_run_cmd.sh
enpt_enmapboxapp-0.7.6.dist-info/AUTHORS.rst
enpt_enmapboxapp-0.7.6.dist-info/LICENSE
enpt_enmapboxapp-0.7.6.dist-info/METADATA
enpt_enmapboxapp-0.7.6.dist-info/WHEEL
enpt_enmapboxapp-0.7.6.dist-info/top_level.txt
enpt_enmapboxapp-0.7.6.dist-info/RECORD
