Metadata-Version: 2.1
Name: enpt-enmapboxapp
Version: 0.7.6
Summary: A QGIS EnMAPBox plugin providing a GUI for the EnMAP processing tools (EnPT).
Home-page: https://git.gfz-potsdam.de/EnMAP/GFZ_Tools_EnMAP_BOX/enpt_enmapboxapp
Author: Daniel Scheffler
Author-email: danschef@gfz-potsdam.de
License: GPL-3.0-or-later
Keywords: enpt_enmapboxapp,EnMAP,EnMAP-Box,hyperspectral,remote sensing,satellite,processing chain
Classifier: Development Status :: 4 - Beta
Classifier: Intended Audience :: End Users/Desktop
Classifier: License :: OSI Approved :: GNU General Public License v3 or later (GPLv3+)
Classifier: Natural Language :: English
Classifier: Programming Language :: Python :: 3.7
Classifier: Programming Language :: Python :: 3.8
Classifier: Programming Language :: Python :: 3.9
Classifier: Programming Language :: Python :: 3.10
Requires-Python: >=3.7
License-File: LICENSE
License-File: AUTHORS.rst
Requires-Dist: importlib-metadata
Requires-Dist: packaging
Requires-Dist: psutil
Provides-Extra: dev
Requires-Dist: importlib-metadata ; extra == 'dev'
Requires-Dist: packaging ; extra == 'dev'
Requires-Dist: pytest ; extra == 'dev'
Requires-Dist: pytest-cov ; extra == 'dev'
Requires-Dist: pytest-reporter-html1 ; extra == 'dev'
Requires-Dist: urlchecker ; extra == 'dev'
Requires-Dist: sphinx-argparse ; extra == 'dev'
Requires-Dist: sphinx-rtd-theme ; extra == 'dev'
Requires-Dist: flake8 ; extra == 'dev'
Requires-Dist: pycodestyle ; extra == 'dev'
Requires-Dist: pydocstyle ; extra == 'dev'
Provides-Extra: doc
Requires-Dist: sphinx-argparse ; extra == 'doc'
Requires-Dist: sphinx-rtd-theme ; extra == 'doc'
Provides-Extra: lint
Requires-Dist: flake8 ; extra == 'lint'
Requires-Dist: pycodestyle ; extra == 'lint'
Requires-Dist: pydocstyle ; extra == 'lint'
Provides-Extra: test
Requires-Dist: pytest ; extra == 'test'
Requires-Dist: pytest-cov ; extra == 'test'
Requires-Dist: pytest-reporter-html1 ; extra == 'test'
Requires-Dist: urlchecker ; extra == 'test'
